pl_fuzzy_frame_match/__init__.py
pl_fuzzy_frame_match/_utils.py
pl_fuzzy_frame_match/matcher.py
pl_fuzzy_frame_match/models.py
pl_fuzzy_frame_match/output_column_name_utils.py
pl_fuzzy_frame_match/pre_process.py
pl_fuzzy_frame_match/process.py
pl_fuzzy_frame_match-0.5.0.dist-info/LICENSE
pl_fuzzy_frame_match-0.5.0.dist-info/METADATA
pl_fuzzy_frame_match-0.5.0.dist-info/WHEEL
pl_fuzzy_frame_match-0.5.0.dist-info/RECORD
