Metadata-Version: 2.1
Name: pl-fuzzy-frame-match
Version: 0.5.0
Summary: Efficient fuzzy matching for Polars DataFrames with support for multiple string similarity algorithms
Home-page: https://github.com/edwardvaneechoud/pl-fuzzy-frame-match
License: MIT
Keywords: polars,fuzzy,matching,string,similarity,dataframe
Author: Edward van Eechoud
Author-email: evaneechoud@gmail.com
Requires-Python: >=3.10,<4.0
Classifier: Development Status :: 3 - Alpha
Classifier: Intended Audience :: Developers
Classifier: License :: OSI Approved :: MIT License
Classifier: Programming Language :: Python :: 3
Classifier: Programming Language :: Python :: 3.10
Classifier: Programming Language :: Python :: 3.11
Classifier: Programming Language :: Python :: 3.12
Classifier: Topic :: Scientific/Engineering :: Information Analysis
Classifier: Topic :: Software Development :: Libraries :: Python Modules
Requires-Dist: polars (>=1.8.2,<1.32.0) ; sys_platform != "win32"
Requires-Dist: polars (>=1.8.2,<=1.25.2) ; sys_platform == "win32"
Requires-Dist: polars-distance (>=0.4.3,<0.5.0)
Requires-Dist: polars-simed (>=0.3.4,<0.4.0)
Project-URL: Documentation, https://github.com/edwardvaneechoud/pl-fuzzy-frame-match
Project-URL: Repository, https://github.com/edwardvaneechoud/pl-fuzzy-frame-match
